{
  "type": "Feature",
  "properties": {
    "uuid": "DEBE12YYJ000000F",
    "sch": "110000121209",
    "nam": "Wittenau",
    "gdf": 5896049,
    "bezeich": "AX_KommunalesGebiet"
  },
  "geometry": {
    "type": "MultiPolygon",
    "coordinates": [
      [
        [
          [
            387837.696,
            5829727.526
          ],
          [
            387837.279,
            5829727.996
          ],
          [
            387833.036,
            5829732.775
          ],
          [
            387799.725,
            5829770.322
          ],
          [
            387796.798,
            5829773.621
          ],
          [
            387790.99,
            5829780.169
          ],
          [
            387784.38,
            5829787.619
          ],
          [
            387779.473,
            5829793.15
          ],
          [
            387760.891,
            5829814.095
          ],
          [
            387755.624,
            5829820.032
          ],
          [
            387755.262,
            5829820.44
          ],
          [
            387707.529,
            5829873.637
          ],
          [
            387703.67,
            5829877.938
          ],
          [
            387701.066,
            5829880.847
          ],
          [
            387707.56,
            5829883.703
          ],
          [
            387701.158,
            5829892.525
          ],
          [
            387703.298,
            5829893.054
          ],
          [
            387699.845,
            5829896.843
          ],
          [
            387686.206,
            5829911.788
          ],
          [
            387672.67,
            5829926.625
          ],
          [
            387659.133,
            5829941.452
          ],
          [
            387645.587,
            5829956.309
          ],
          [
            387632.08,
            5829971.105
          ],
          [
            387624.665,
            5829979.235
          ],
          [
            387618.563,
            5829985.921
          ],
          [
            387610.958,
            5829989.806
          ],
          [
            387607.392,
            5829991.584
          ],
          [
            387601.129,
            5829992.473
          ],
          [
            387578.702,
            5829991.48
          ],
          [
            387566.711,
            5829990.952
          ],
          [
            387561.749,
            5829990.733
          ],
          [
            387559.892,
            5829990.651
          ],
          [
            387552.882,
            5829990.342
          ],
          [
            387541.956,
            5829986.33
          ],
          [
            387530.67,
            5829980.696
          ],
          [
            387515.478,
            5829970.566
          ],
          [
            387507.729,
            5829963.784
          ],
          [
            387500.724,
            5829955.618
          ],
          [
            387494.157,
            5829946.304
          ],
          [
            387482.716,
            5829922.594
          ],
          [
            387478.278,
            5829915.839
          ],
          [
            387472.412,
            5829910.261
          ],
          [
            387443.299,
            5829890.047
          ],
          [
            387433.749,
            5829882.649
          ],
          [
            387427.801,
            5829876.963
          ],
          [
            387419.966,
            5829865.663
          ],
          [
            387415.928,
            5829856.791
          ],
          [
            387402.392,
            5829814.442
          ],
          [
            387392.089,
            5829779.635
          ],
          [
            387390.615,
            5829775.209
          ],
          [
            387383.151,
            5829762.342
          ],
          [
            387374.99,
            5829752.318
          ],
          [
            387367.551,
            5829745
          ],
          [
            387357.875,
            5829736.775
          ],
          [
            387325.388,
            5829719.975
          ],
          [
            387263.567,
            5829690.624
          ],
          [
            387236.04,
            5829678.036
          ],
          [
            387211.539,
            5829666.932
          ],
          [
            387192.151,
            5829664.748
          ],
          [
            387168.63,
            5829663.467
          ],
          [
            387168.15,
            5829664.347
          ],
          [
            387106.185,
            5829661.94
          ],
          [
            387102.134,
            5829662.278
          ],
          [
            387098.658,
            5829663.491
          ],
          [
            387096.05,
            5829666.081
          ],
          [
            387089.05,
            5829675.631
          ],
          [
            387086.293,
            5829678.402
          ],
          [
            387084.045,
            5829680.02
          ],
          [
            387084.813,
            5829683.907
          ],
          [
            387069.904,
            5829684.878
          ],
          [
            387057.111,
            5829685.712
          ],
          [
            387027.472,
            5829692.005
          ],
          [
            386998.339,
            5829699.89
          ],
          [
            386969.057,
            5829711.323
          ],
          [
            386941.343,
            5829727.28
          ],
          [
            386928.693,
            5829734.56
          ],
          [
            386920.691,
            5829739.163
          ],
          [
            386913.388,
            5829742.121
          ],
          [
            386905.526,
            5829743.071
          ],
          [
            386897.777,
            5829742.019
          ],
          [
            386888.775,
            5829739.233
          ],
          [
            386888.493,
            5829739.146
          ],
          [
            386879.553,
            5829735.476
          ],
          [
            386870.761,
            5829731.134
          ],
          [
            386864.001,
            5829728.002
          ],
          [
            386849.376,
            5829721.228
          ],
          [
            386846.731,
            5829720.003
          ],
          [
            386848.149,
            5829717.296
          ],
          [
            386851.044,
            5829711.791
          ],
          [
            386832.297,
            5829704.539
          ],
          [
            386827.889,
            5829701.463
          ],
          [
            386827.468,
            5829700.861
          ],
          [
            386824.332,
            5829696.351
          ],
          [
            386821.578,
            5829692.449
          ],
          [
            386816.971,
            5829685.92
          ],
          [
            386817.073,
            5829681.251
          ],
          [
            386837.808,
            5829658.572
          ],
          [
            386850.884,
            5829644.27
          ],
          [
            386852.025,
            5829640.227
          ],
          [
            386848.149,
            5829636.993
          ],
          [
            386840.817,
            5829630.877
          ],
          [
            386834.993,
            5829626.019
          ],
          [
            386812.534,
            5829604.668
          ],
          [
            386808.613,
            5829605.436
          ],
          [
            386777.612,
            5829644.881
          ],
          [
            386776.392,
            5829646.432
          ],
          [
            386757.068,
            5829658.057
          ],
          [
            386751.881,
            5829661.367
          ],
          [
            386746.225,
            5829664.975
          ],
          [
            386739.278,
            5829668.476
          ],
          [
            386731.351,
            5829672.322
          ],
          [
            386697.626,
            5829686.74
          ],
          [
            386671.867,
            5829697.752
          ],
          [
            386667.139,
            5829701.064
          ],
          [
            386662.847,
            5829706.028
          ],
          [
            386627.198,
            5829747.26
          ],
          [
            386619.831,
            5829753.632
          ],
          [
            386618.538,
            5829754.75
          ],
          [
            386620.112,
            5829751.837
          ],
          [
            386600.43,
            5829743.743
          ],
          [
            386599.83,
            5829745.117
          ],
          [
            386557.353,
            5829751.431
          ],
          [
            386510.359,
            5829758.416
          ],
          [
            386449.177,
            5829726.121
          ],
          [
            386423.436,
            5829712.006
          ],
          [
            386419.168,
            5829709.666
          ],
          [
            386413.635,
            5829706.633
          ],
          [
            386412.1,
            5829705.813
          ],
          [
            386401.654,
            5829700.252
          ],
          [
            386402.243,
            5829699.141
          ],
          [
            386398.84,
            5829688.386
          ],
          [
            386397.572,
            5829684.381
          ],
          [
            386394.822,
            5829675.665
          ],
          [
            386391.06,
            5829663.746
          ],
          [
            386387.858,
            5829662.087
          ],
          [
            386369.115,
            5829652.375
          ],
          [
            386367.611,
            5829652.184
          ],
          [
            386347.725,
            5829649.683
          ],
          [
            386347.264,
            5829649.622
          ],
          [
            386333.736,
            5829646.01
          ],
          [
            386324.507,
            5829641.826
          ],
          [
            386322.893,
            5829641.096
          ],
          [
            386316.596,
            5829636.446
          ],
          [
            386313.841,
            5829634.412
          ],
          [
            386302.71,
            5829626.192
          ],
          [
            386301.657,
            5829625.416
          ],
          [
            386294.232,
            5829619.944
          ],
          [
            386282.731,
            5829616.213
          ],
          [
            386272.815,
            5829610.612
          ],
          [
            386266.115,
            5829605.82
          ],
          [
            386260.986,
            5829601.61
          ],
          [
            386257.835,
            5829599.025
          ],
          [
            386250.552,
            5829593.048
          ],
          [
            386241.544,
            5829587.32
          ],
          [
            386238.273,
            5829586.33
          ],
          [
            386227.714,
            5829583.136
          ],
          [
            386224.316,
            5829582.108
          ],
          [
            386219.901,
            5829582.192
          ],
          [
            386214.88,
            5829582.288
          ],
          [
            386214.65,
            5829582.244
          ],
          [
            386192.323,
            5829577.988
          ],
          [
            386191.035,
            5829577.743
          ],
          [
            386190.183,
            5829577.283
          ],
          [
            386184.286,
            5829574.101
          ],
          [
            386177.949,
            5829570.075
          ],
          [
            386174.093,
            5829567.626
          ],
          [
            386160.566,
            5829563.815
          ],
          [
            386130.253,
            5829555.275
          ],
          [
            386124.985,
            5829553.791
          ],
          [
            386120.801,
            5829552.612
          ],
          [
            386091.95,
            5829530.423
          ],
          [
            386087.564,
            5829524.665
          ],
          [
            386086.319,
            5829523.031
          ],
          [
            386085.431,
            5829521.065
          ],
          [
            386076.84,
            5829502.033
          ],
          [
            386073.608,
            5829489.286
          ],
          [
            386073.521,
            5829484.747
          ],
          [
            386070.411,
            5829474.773
          ],
          [
            386069.922,
            5829473.207
          ],
          [
            386067.662,
            5829469.903
          ],
          [
            386067.146,
            5829469.15
          ],
          [
            386067.072,
            5829469.041
          ],
          [
            386066.946,
            5829468.929
          ],
          [
            386059.351,
            5829462.139
          ],
          [
            386052.551,
            5829457.869
          ],
          [
            386048.08,
            5829456.668
          ],
          [
            386042.57,
            5829455.189
          ],
          [
            386038.923,
            5829455.001
          ],
          [
            386008.659,
            5829453.445
          ],
          [
            385999.963,
            5829454.161
          ],
          [
            385984.126,
            5829452.09
          ],
          [
            385971.795,
            5829450.478
          ],
          [
            385958.975,
            5829447.023
          ],
          [
            385949.471,
            5829440.578
          ],
          [
            385945.592,
            5829435.955
          ],
          [
            385938.689,
            5829409.742
          ],
          [
            385938.576,
            5829409.312
          ],
          [
            385935.536,
            5829402.549
          ],
          [
            385930.824,
            5829396.507
          ],
          [
            385921.57,
            5829389.905
          ],
          [
            385915.266,
            5829387.21
          ],
          [
            385914.088,
            5829387.184
          ],
          [
            385910.412,
            5829387.102
          ],
          [
            385908.367,
            5829387.777
          ],
          [
            385898.026,
            5829382.67
          ],
          [
            385889.918,
            5829378.251
          ],
          [
            385888.638,
            5829377.554
          ],
          [
            385883.199,
            5829374.588
          ],
          [
            385881.672,
            5829373.757
          ],
          [
            385865.475,
            5829364.927
          ],
          [
            385862.937,
            5829363.544
          ],
          [
            385861.206,
            5829362.614
          ],
          [
            385819.935,
            5829340.438
          ],
          [
            385816.253,
            5829338.46
          ],
          [
            385793.945,
            5829326.474
          ],
          [
            385776.624,
            5829317.434
          ],
          [
            385775.222,
            5829316.654
          ],
          [
            385760.388,
            5829306.976
          ],
          [
            385744.838,
            5829296.545
          ],
          [
            385743.265,
            5829295.49
          ],
          [
            385742.418,
            5829294.922
          ],
          [
            385727.853,
            5829284.955
          ],
          [
            385723.895,
            5829275.11
          ],
          [
            385719.598,
            5829264.89
          ],
          [
            385717.069,
            5829247.174
          ],
          [
            385716.917,
            5829240.227
          ],
          [
            385716.875,
            5829238.808
          ],
          [
            385719.763,
            5829237.152
          ],
          [
            385721.232,
            5829236.31
          ],
          [
            385725.93,
            5829233.616
          ],
          [
            385738.087,
            5829226.635
          ],
          [
            385751.684,
            5829203.735
          ],
          [
            385754.726,
            5829198.612
          ],
          [
            385764.927,
            5829188.656
          ],
          [
            385784.475,
            5829176.545
          ],
          [
            385800.08,
            5829167.443
          ],
          [
            385806.811,
            5829164.085
          ],
          [
            385813.581,
            5829155.472
          ],
          [
            385816.831,
            5829149.47
          ],
          [
            385824.543,
            5829135.251
          ],
          [
            385827.984,
            5829128.904
          ],
          [
            385830.126,
            5829125.178
          ],
          [
            385833.106,
            5829119.992
          ],
          [
            385838.684,
            5829110.289
          ],
          [
            385841.482,
            5829105.421
          ],
          [
            385844.603,
            5829099.99
          ],
          [
            385851.065,
            5829071.274
          ],
          [
            385855.041,
            5829055.829
          ],
          [
            385856.542,
            5829049.955
          ],
          [
            385860.259,
            5829035.486
          ],
          [
            385867.424,
            5829007.596
          ],
          [
            385872.1,
            5828989.395
          ],
          [
            385875.921,
            5828974.522
          ],
          [
            385875.071,
            5828968.074
          ],
          [
            385874.735,
            5828965.529
          ],
          [
            385874.454,
            5828963.396
          ],
          [
            385867.192,
            5828955.105
          ],
          [
            385865.963,
            5828953.644
          ],
          [
            385852.781,
            5828937.975
          ],
          [
            385852.125,
            5828936.882
          ],
          [
            385849.564,
            5828932.617
          ],
          [
            385840.262,
            5828917.266
          ],
          [
            385833.674,
            5828910.424
          ],
          [
            385832.488,
            5828909.448
          ],
          [
            385830.856,
            5828908.104
          ],
          [
            385822.047,
            5828900.852
          ],
          [
            385821.653,
            5828900.527
          ],
          [
            385781.308,
            5828893.475
          ],
          [
            385742.176,
            5828886.635
          ],
          [
            385731.981,
            5828886.389
          ],
          [
            385725.653,
            5828886.236
          ],
          [
            385723.517,
            5828886.184
          ],
          [
            385715.27,
            5828888.06
          ],
          [
            385684.506,
            5828895.06
          ],
          [
            385678.844,
            5828896.348
          ],
          [
            385674,
            5828896.895
          ],
          [
            385648.968,
            5828899.723
          ],
          [
            385628.675,
            5828902.016
          ],
          [
            385628.201,
            5828902.069
          ],
          [
            385620.602,
            5828903.589
          ],
          [
            385608.669,
            5828905.975
          ],
          [
            385595.723,
            5828902.623
          ],
          [
            385595.349,
            5828902.526
          ],
          [
            385587.63,
            5828900.527
          ],
          [
            385567.743,
            5828892.415
          ],
          [
            385564.045,
            5828891.998
          ],
          [
            385560.882,
            5828893.02
          ],
          [
            385546.183,
            5828903.598
          ],
          [
            385540.309,
            5828907.825
          ],
          [
            385526.561,
            5828917.719
          ],
          [
            385524.245,
            5828918.089
          ],
          [
            385498.641,
            5828922.176
          ],
          [
            385494.095,
            5828921.189
          ],
          [
            385489.443,
            5828918.472
          ],
          [
            385476.358,
            5828910.829
          ],
          [
            385476.232,
            5828910.718
          ],
          [
            385466.575,
            5828902.21
          ],
          [
            385450.173,
            5828887.759
          ],
          [
            385436.108,
            5828875.366
          ],
          [
            385435.355,
            5828874.703
          ],
          [
            385433.439,
            5828872.411
          ],
          [
            385424.262,
            5828861.429
          ],
          [
            385416.764,
            5828850.699
          ],
          [
            385409.686,
            5828840.571
          ],
          [
            385409.091,
            5828839.72
          ],
          [
            385388.032,
            5828815.957
          ],
          [
            385372.82,
            5828797.311
          ],
          [
            385368.91,
            5828793.354
          ],
          [
            385369.548,
            5828792.28
          ],
          [
            385361.68,
            5828784.367
          ],
          [
            385338.634,
            5828761.189
          ],
          [
            385329.088,
            5828751.587
          ],
          [
            385327.803,
            5828750.295
          ],
          [
            385325.925,
            5828748.405
          ],
          [
            385317.037,
            5828739.467
          ],
          [
            385316.753,
            5828739.181
          ],
          [
            385314.142,
            5828736.555
          ],
          [
            385301.489,
            5828722.309
          ],
          [
            385295.962,
            5828716.948
          ],
          [
            385283.577,
            5828712.497
          ],
          [
            385274.471,
            5828705.021
          ],
          [
            385276.488,
            5828705.353
          ],
          [
            385272.179,
            5828701.195
          ],
          [
            385222.506,
            5828678.843
          ],
          [
            385204.744,
            5828665.522
          ],
          [
            385197.903,
            5828659.712
          ],
          [
            385183.954,
            5828650.269
          ],
          [
            385173.839,
            5828642.655
          ],
          [
            385169.092,
            5828639.083
          ],
          [
            385163.801,
            5828633.754
          ],
          [
            385153.674,
            5828625.457
          ],
          [
            385142.198,
            5828616.706
          ],
          [
            385122.253,
            5828600.637
          ],
          [
            385120.257,
            5828598.96
          ],
          [
            385111.207,
            5828591.358
          ],
          [
            385110.118,
            5828590.544
          ],
          [
            385078.453,
            5828566.884
          ],
          [
            385070.068,
            5828564.474
          ],
          [
            385060.164,
            5828560.063
          ],
          [
            385029.707,
            5828550.123
          ],
          [
            384973.983,
            5828529.786
          ],
          [
            384948.09,
            5828515.318
          ],
          [
            384938.851,
            5828510.156
          ],
          [
            384930.23,
            5828505.339
          ],
          [
            384927.533,
            5828503.832
          ],
          [
            384917.687,
            5828498.33
          ],
          [
            384945.469,
            5828486.962
          ],
          [
            384969.635,
            5828475.373
          ],
          [
            384986.827,
            5828466.046
          ],
          [
            384995.189,
            5828461.51
          ],
          [
            385017.575,
            5828448.495
          ],
          [
            385026.306,
            5828443.374
          ],
          [
            385046.149,
            5828431.638
          ],
          [
            385065.114,
            5828419.378
          ],
          [
            385083.967,
            5828406.42
          ],
          [
            385097.277,
            5828397.059
          ],
          [
            385126.743,
            5828373.807
          ],
          [
            385146.816,
            5828356.726
          ],
          [
            385179.239,
            5828326.511
          ],
          [
            385215.972,
            5828290.584
          ],
          [
            385231.662,
            5828274.346
          ],
          [
            385246.282,
            5828258.139
          ],
          [
            385254.324,
            5828250.926
          ],
          [
            385256.32,
            5828249.138
          ],
          [
            385266.674,
            5828239.372
          ],
          [
            385267.425,
            5828238.668
          ],
          [
            385278.496,
            5828228.179
          ],
          [
            385263.812,
            5828225.993
          ],
          [
            385261.265,
            5828225.614
          ],
          [
            385239.963,
            5828222.441
          ],
          [
            385248.337,
            5828219.542
          ],
          [
            385269.448,
            5828197.198
          ],
          [
            385272.773,
            5828193.679
          ],
          [
            385277.654,
            5828188.516
          ],
          [
            385278.958,
            5828187.131
          ],
          [
            385281.773,
            5828184.168
          ],
          [
            385284.637,
            5828181.254
          ],
          [
            385287.551,
            5828178.388
          ],
          [
            385290.501,
            5828175.544
          ],
          [
            385293.485,
            5828172.733
          ],
          [
            385296.5,
            5828169.958
          ],
          [
            385299.556,
            5828167.232
          ],
          [
            385302.649,
            5828164.546
          ],
          [
            385305.776,
            5828161.902
          ],
          [
            385308.948,
            5828159.3
          ],
          [
            385312.146,
            5828156.73
          ],
          [
            385315.368,
            5828154.19
          ],
          [
            385345.78,
            5828130.733
          ],
          [
            385435.348,
            5828061.652
          ],
          [
            385440.4,
            5828057.762
          ],
          [
            385445.473,
            5828053.899
          ],
          [
            385450.567,
            5828050.063
          ],
          [
            385455.677,
            5828046.252
          ],
          [
            385460.804,
            5828042.464
          ],
          [
            385465.949,
            5828038.7
          ],
          [
            385471.111,
            5828034.951
          ],
          [
            385476.29,
            5828031.226
          ],
          [
            385481.486,
            5828027.525
          ],
          [
            385486.701,
            5828023.854
          ],
          [
            385491.931,
            5828020.205
          ],
          [
            385497.176,
            5828016.577
          ],
          [
            385502.437,
            5828012.965
          ],
          [
            385507.715,
            5828009.378
          ],
          [
            385513.01,
            5828005.816
          ],
          [
            385518.317,
            5828002.288
          ],
          [
            385523.64,
            5827998.784
          ],
          [
            385528.979,
            5827995.303
          ],
          [
            385534.334,
            5827991.836
          ],
          [
            385539.704,
            5827988.394
          ],
          [
            385545.091,
            5827984.977
          ],
          [
            385550.498,
            5827981.586
          ],
          [
            385555.921,
            5827978.22
          ],
          [
            385561.358,
            5827974.878
          ],
          [
            385566.802,
            5827971.566
          ],
          [
            385572.259,
            5827968.276
          ],
          [
            385577.729,
            5827965.007
          ],
          [
            385582.982,
            5827961.911
          ],
          [
            385588.246,
            5827958.834
          ],
          [
            385593.522,
            5827955.777
          ],
          [
            385594.254,
            5827955.353
          ],
          [
            385599.788,
            5827952.183
          ],
          [
            385605.338,
            5827949.041
          ],
          [
            385610.903,
            5827945.926
          ],
          [
            385616.477,
            5827942.832
          ],
          [
            385622.065,
            5827939.762
          ],
          [
            385627.667,
            5827936.718
          ],
          [
            385633.289,
            5827933.698
          ],
          [
            385638.925,
            5827930.704
          ],
          [
            385644.575,
            5827927.736
          ],
          [
            385650.229,
            5827924.796
          ],
          [
            385655.897,
            5827921.882
          ],
          [
            385661.577,
            5827918.993
          ],
          [
            385711.137,
            5827893.931
          ],
          [
            385738.654,
            5827879.99
          ],
          [
            385743.711,
            5827877.409
          ],
          [
            385741.512,
            5827875.85
          ],
          [
            385798.02,
            5827851.755
          ],
          [
            385852.495,
            5827830.033
          ],
          [
            385862.356,
            5827826.433
          ],
          [
            385889.38,
            5827816.57
          ],
          [
            385923.584,
            5827804.528
          ],
          [
            385971.246,
            5827789.401
          ],
          [
            385976.273,
            5827787.851
          ],
          [
            385981.927,
            5827786.162
          ],
          [
            385998.396,
            5827778.745
          ],
          [
            386004.961,
            5827776.125
          ],
          [
            386011.748,
            5827773.546
          ],
          [
            386018.503,
            5827770.887
          ],
          [
            386025.226,
            5827768.146
          ],
          [
            386031.916,
            5827765.325
          ],
          [
            386038.571,
            5827762.424
          ],
          [
            386045.191,
            5827759.443
          ],
          [
            386052.193,
            5827756.214
          ],
          [
            386059.157,
            5827752.904
          ],
          [
            386066.083,
            5827749.513
          ],
          [
            386072.968,
            5827746.042
          ],
          [
            386079.812,
            5827742.491
          ],
          [
            386086.615,
            5827738.86
          ],
          [
            386100.126,
            5827731.483
          ],
          [
            386145.571,
            5827718.001
          ],
          [
            386135.539,
            5827699.643
          ],
          [
            386139.164,
            5827700.392
          ],
          [
            386142.793,
            5827701.117
          ],
          [
            386146.428,
            5827701.818
          ],
          [
            386148.45,
            5827702.197
          ],
          [
            386150.474,
            5827702.568
          ],
          [
            386152.499,
            5827702.931
          ],
          [
            386154.525,
            5827703.287
          ],
          [
            386156.553,
            5827703.635
          ],
          [
            386158.582,
            5827703.976
          ],
          [
            386164.16,
            5827704.871
          ],
          [
            386169.748,
            5827705.708
          ],
          [
            386175.343,
            5827706.487
          ],
          [
            386180.947,
            5827707.207
          ],
          [
            386188.634,
            5827707.85
          ],
          [
            386196.329,
            5827708.384
          ],
          [
            386204.031,
            5827708.807
          ],
          [
            386211.739,
            5827709.12
          ],
          [
            386219.45,
            5827709.323
          ],
          [
            386227.163,
            5827709.416
          ],
          [
            386233.771,
            5827709.502
          ],
          [
            386240.379,
            5827709.496
          ],
          [
            386246.987,
            5827709.4
          ],
          [
            386253.592,
            5827709.212
          ],
          [
            386260.195,
            5827708.932
          ],
          [
            386266.793,
            5827708.562
          ],
          [
            386273.385,
            5827708.1
          ],
          [
            386419.85,
            5827696.732
          ],
          [
            386424.339,
            5827690.144
          ],
          [
            386412.581,
            5827668.967
          ],
          [
            386410.879,
            5827665.902
          ],
          [
            386410.118,
            5827664.112
          ],
          [
            386387.755,
            5827612.086
          ],
          [
            386379.269,
            5827596.836
          ],
          [
            386353.649,
            5827550.795
          ],
          [
            386337.002,
            5827520.879
          ],
          [
            386329.703,
            5827507.769
          ],
          [
            386319.794,
            5827489.949
          ],
          [
            386225.499,
            5827320.671
          ],
          [
            386198.764,
            5827272.679
          ],
          [
            386091.534,
            5827080.193
          ],
          [
            386075.241,
            5827050.946
          ],
          [
            386065.86,
            5827034.107
          ],
          [
            386008.824,
            5826931.72
          ],
          [
            385938.329,
            5826805.161
          ],
          [
            385896.74,
            5826730.488
          ],
          [
            385895.17,
            5826727.671
          ],
          [
            385876.013,
            5826693.286
          ],
          [
            385867.71,
            5826678.385
          ],
          [
            385855.379,
            5826656.241
          ],
          [
            385844.601,
            5826636.888
          ],
          [
            385851.455,
            5826637.107
          ],
          [
            385872.86,
            5826638.48
          ],
          [
            385873.651,
            5826638.535
          ],
          [
            385879.652,
            5826638.501
          ],
          [
            385898.482,
            5826638.398
          ],
          [
            385906.634,
            5826638.352
          ],
          [
            385933.332,
            5826638.205
          ],
          [
            385944.424,
            5826638.215
          ],
          [
            385987.131,
            5826638.253
          ],
          [
            386039.781,
            5826648.311
          ],
          [
            386060.872,
            5826652.34
          ],
          [
            386099.259,
            5826659.727
          ],
          [
            386101.722,
            5826660.278
          ],
          [
            386125.362,
            5826664.66
          ],
          [
            386132.439,
            5826666.125
          ],
          [
            386152.4,
            5826669.915
          ],
          [
            386153.624,
            5826670.151
          ],
          [
            386160.549,
            5826671.479
          ],
          [
            386173.435,
            5826673.199
          ],
          [
            386180.488,
            5826674.163
          ],
          [
            386195.246,
            5826676.178
          ],
          [
            386208.415,
            5826677.945
          ],
          [
            386236.258,
            5826681.681
          ],
          [
            386264.063,
            5826685.411
          ],
          [
            386291.966,
            5826689.155
          ],
          [
            386317.952,
            5826692.641
          ],
          [
            386343.86,
            5826696.123
          ],
          [
            386349.488,
            5826696.88
          ],
          [
            386354.443,
            5826697.546
          ],
          [
            386369.709,
            5826703.627
          ],
          [
            386395.631,
            5826713.954
          ],
          [
            386399.232,
            5826715.388
          ],
          [
            386414.091,
            5826721.308
          ],
          [
            386421.763,
            5826721.5
          ],
          [
            386428.759,
            5826721.675
          ],
          [
            386447.681,
            5826722.147
          ],
          [
            386477.216,
            5826722.886
          ],
          [
            386489.022,
            5826723.181
          ],
          [
            386503.76,
            5826716.304
          ],
          [
            386529.999,
            5826703.917
          ],
          [
            386533.578,
            5826702.228
          ],
          [
            386558.332,
            5826690.696
          ],
          [
            386589.027,
            5826676.394
          ],
          [
            386614.625,
            5826663.904
          ],
          [
            386619.853,
            5826661.285
          ],
          [
            386630.316,
            5826656.046
          ],
          [
            386664.495,
            5826661.741
          ],
          [
            386685.284,
            5826661.212
          ],
          [
            386704.896,
            5826660.712
          ],
          [
            386733.931,
            5826662.3
          ],
          [
            386744.049,
            5826661.494
          ],
          [
            386753.774,
            5826660.719
          ],
          [
            386784.23,
            5826658.65
          ],
          [
            386827.016,
            5826661.415
          ],
          [
            386851.493,
            5826663.752
          ],
          [
            386877.083,
            5826665.929
          ],
          [
            386907.707,
            5826664.528
          ],
          [
            386959.457,
            5826665.722
          ],
          [
            387008.682,
            5826666.588
          ],
          [
            387027.104,
            5826667.32
          ],
          [
            387034.837,
            5826667.622
          ],
          [
            387034.431,
            5826665.668
          ],
          [
            387033.109,
            5826659.306
          ],
          [
            387033.199,
            5826659.314
          ],
          [
            387050.536,
            5826659.734
          ],
          [
            387051.056,
            5826659.724
          ],
          [
            387054.501,
            5826666.328
          ],
          [
            387055.666,
            5826667.616
          ],
          [
            387061.028,
            5826673.543
          ],
          [
            387061.227,
            5826674.509
          ],
          [
            387064.308,
            5826674.591
          ],
          [
            387127.907,
            5826676.34
          ],
          [
            387217.601,
            5826677.412
          ],
          [
            387283.439,
            5826679.138
          ],
          [
            387305.833,
            5826683.621
          ],
          [
            387309.266,
            5826684.306
          ],
          [
            387339.894,
            5826691.132
          ],
          [
            387344.799,
            5826694.028
          ],
          [
            387471.184,
            5826737.849
          ],
          [
            387502.276,
            5826749.086
          ],
          [
            387500.892,
            5826754.102
          ],
          [
            387500.583,
            5826755.208
          ],
          [
            387498.447,
            5826762.748
          ],
          [
            387498.25,
            5826763.461
          ],
          [
            387504.677,
            5826764.869
          ],
          [
            387513.504,
            5826766.881
          ],
          [
            387521.315,
            5826769.032
          ],
          [
            387538.355,
            5826774.357
          ],
          [
            387538.973,
            5826774.559
          ],
          [
            387552.13,
            5826778.864
          ],
          [
            387562.722,
            5826782.672
          ],
          [
            387594.988,
            5826796.777
          ],
          [
            387627.703,
            5826811.312
          ],
          [
            387640.782,
            5826817.123
          ],
          [
            387668.162,
            5826829.311
          ],
          [
            387693.507,
            5826840.59
          ],
          [
            387704.709,
            5826845.574
          ],
          [
            387714.75,
            5826850.042
          ],
          [
            387726.317,
            5826855.191
          ],
          [
            387762.041,
            5826871.09
          ],
          [
            387773.547,
            5826876.211
          ],
          [
            387779.822,
            5826879.003
          ],
          [
            387786.264,
            5826881.87
          ],
          [
            387839.674,
            5826905.64
          ],
          [
            387879.932,
            5826923.562
          ],
          [
            387882.221,
            5826924.578
          ],
          [
            387884.521,
            5826925.604
          ],
          [
            387905.411,
            5826934.106
          ],
          [
            387906.742,
            5826934.66
          ],
          [
            387900.369,
            5826949.191
          ],
          [
            387898.681,
            5826952.982
          ],
          [
            387896.88,
            5826957.136
          ],
          [
            387892.75,
            5826966.544
          ],
          [
            387888.724,
            5826975.7
          ],
          [
            387881.478,
            5826992.167
          ],
          [
            387877.463,
            5827001.323
          ],
          [
            387810.053,
            5827154.65
          ],
          [
            387810.63,
            5827155.217
          ],
          [
            387811.122,
            5827155.861
          ],
          [
            387811.517,
            5827156.567
          ],
          [
            387811.808,
            5827157.323
          ],
          [
            387811.988,
            5827158.112
          ],
          [
            387812.056,
            5827158.918
          ],
          [
            387812.008,
            5827159.727
          ],
          [
            387811.846,
            5827160.52
          ],
          [
            387811.574,
            5827161.282
          ],
          [
            387811.196,
            5827161.998
          ],
          [
            387810.721,
            5827162.652
          ],
          [
            387810.158,
            5827163.233
          ],
          [
            387809.518,
            5827163.729
          ],
          [
            387808.815,
            5827164.129
          ],
          [
            387808.062,
            5827164.425
          ],
          [
            387807.275,
            5827164.611
          ],
          [
            387806.469,
            5827164.685
          ],
          [
            387805.661,
            5827164.643
          ],
          [
            387792.461,
            5827194.667
          ],
          [
            387791.104,
            5827197.752
          ],
          [
            387787.844,
            5827205.168
          ],
          [
            387776.848,
            5827230.182
          ],
          [
            387746.604,
            5827299.023
          ],
          [
            387744.071,
            5827304.79
          ],
          [
            387742.508,
            5827308.31
          ],
          [
            387687.123,
            5827434.405
          ],
          [
            387677.121,
            5827457.154
          ],
          [
            387677.05,
            5827457.315
          ],
          [
            387672.134,
            5827468.518
          ],
          [
            387661.314,
            5827493.142
          ],
          [
            387651.25,
            5827516.012
          ],
          [
            387640.171,
            5827541.251
          ],
          [
            387629.513,
            5827565.492
          ],
          [
            387622.445,
            5827582.039
          ],
          [
            387615.041,
            5827598.385
          ],
          [
            387612.722,
            5827603.669
          ],
          [
            387601.623,
            5827628.929
          ],
          [
            387591.45,
            5827652.089
          ],
          [
            387579.389,
            5827679.548
          ],
          [
            387576.907,
            5827685.205
          ],
          [
            387556.934,
            5827730.662
          ],
          [
            387547.369,
            5827752.443
          ],
          [
            387542.716,
            5827763.03
          ],
          [
            387540.938,
            5827767.074
          ],
          [
            387545.841,
            5827768.301
          ],
          [
            387560.359,
            5827771.924
          ],
          [
            387566.182,
            5827773.633
          ],
          [
            387625.654,
            5827795.509
          ],
          [
            387657.626,
            5827807.289
          ],
          [
            387751.475,
            5827841.729
          ],
          [
            387845.271,
            5827876.48
          ],
          [
            387920.202,
            5827904.219
          ],
          [
            387933.81,
            5827909.842
          ],
          [
            387969.337,
            5827924.514
          ],
          [
            387969.538,
            5827924.6
          ],
          [
            388005.277,
            5827939.358
          ],
          [
            388008.703,
            5827935.933
          ],
          [
            388053.552,
            5827954.043
          ],
          [
            388055.147,
            5827960.047
          ],
          [
            388045.036,
            5827969.399
          ],
          [
            387986.61,
            5828024.069
          ],
          [
            387961.852,
            5828051.317
          ],
          [
            387960.316,
            5828052.816
          ],
          [
            387955.476,
            5828057.307
          ],
          [
            387940.204,
            5828071.479
          ],
          [
            387917.609,
            5828092.44
          ],
          [
            387906.743,
            5828102.234
          ],
          [
            387901.014,
            5828107.901
          ],
          [
            387897.652,
            5828110.925
          ],
          [
            387895.152,
            5828113.283
          ],
          [
            387889.982,
            5828118.159
          ],
          [
            387875.628,
            5828131.695
          ],
          [
            387856.21,
            5828150.008
          ],
          [
            387840.84,
            5828164.502
          ],
          [
            387826.239,
            5828178.272
          ],
          [
            387812.439,
            5828191.286
          ],
          [
            387797.802,
            5828205.09
          ],
          [
            387788.164,
            5828214.103
          ],
          [
            387782.459,
            5828216.401
          ],
          [
            387709.237,
            5828286.43
          ],
          [
            387687.56,
            5828306.422
          ],
          [
            387647.288,
            5828345.056
          ],
          [
            387616.888,
            5828372.233
          ],
          [
            387551.647,
            5828432.311
          ],
          [
            387546.778,
            5828436.964
          ],
          [
            387500.373,
            5828481.314
          ],
          [
            387439.491,
            5828539.249
          ],
          [
            387415.248,
            5828562.145
          ],
          [
            387402.272,
            5828574.399
          ],
          [
            387391.871,
            5828584.223
          ],
          [
            387389.168,
            5828587.146
          ],
          [
            387391.814,
            5828599.991
          ],
          [
            387386.095,
            5828601.836
          ],
          [
            387367.428,
            5828619.763
          ],
          [
            387315.862,
            5828669.667
          ],
          [
            387335.651,
            5828690.389
          ],
          [
            387331.626,
            5828695.374
          ],
          [
            387333.502,
            5828697.085
          ],
          [
            387332.088,
            5828717.592
          ],
          [
            387317.836,
            5828716.823
          ],
          [
            387313.941,
            5828738.855
          ],
          [
            387318.942,
            5828746.166
          ],
          [
            387325.618,
            5828754.891
          ],
          [
            387332.516,
            5828763.906
          ],
          [
            387342.285,
            5828776.706
          ],
          [
            387351.973,
            5828789.329
          ],
          [
            387366.966,
            5828808.94
          ],
          [
            387381.959,
            5828828.576
          ],
          [
            387392.496,
            5828841.587
          ],
          [
            387401.529,
            5828853.063
          ],
          [
            387403.567,
            5828855.652
          ],
          [
            387405.168,
            5828857.623
          ],
          [
            387413.001,
            5828867.265
          ],
          [
            387413.971,
            5828868.462
          ],
          [
            387424.016,
            5828881.154
          ],
          [
            387443.558,
            5828905.914
          ],
          [
            387452.142,
            5828917.066
          ],
          [
            387463.585,
            5828926.455
          ],
          [
            387476.131,
            5828936.378
          ],
          [
            387490.443,
            5828948.015
          ],
          [
            387502.529,
            5828957.89
          ],
          [
            387506.919,
            5828961.681
          ],
          [
            387507.581,
            5828962.228
          ],
          [
            387511.45,
            5828965.421
          ],
          [
            387525.533,
            5828976.936
          ],
          [
            387537.756,
            5828987.068
          ],
          [
            387550.23,
            5828997.067
          ],
          [
            387562.634,
            5829007.348
          ],
          [
            387575.033,
            5829017.425
          ],
          [
            387587.231,
            5829027.634
          ],
          [
            387599.64,
            5829038.168
          ],
          [
            387611.912,
            5829048.222
          ],
          [
            387624.24,
            5829058.505
          ],
          [
            387635.27,
            5829067.758
          ],
          [
            387642.187,
            5829073.749
          ],
          [
            387643.365,
            5829074.696
          ],
          [
            387645.083,
            5829076.154
          ],
          [
            387650.876,
            5829081.063
          ],
          [
            387653.89,
            5829083.608
          ],
          [
            387666.715,
            5829094.442
          ],
          [
            387679.856,
            5829105.542
          ],
          [
            387690.734,
            5829114.731
          ],
          [
            387692.984,
            5829116.52
          ],
          [
            387702.857,
            5829124.37
          ],
          [
            387706.159,
            5829126.792
          ],
          [
            387719.727,
            5829136.746
          ],
          [
            387727.327,
            5829142.322
          ],
          [
            387733.404,
            5829146.646
          ],
          [
            387744.985,
            5829154.885
          ],
          [
            387745.989,
            5829155.418
          ],
          [
            387761.004,
            5829163.383
          ],
          [
            387763.535,
            5829164.726
          ],
          [
            387776.162,
            5829171.425
          ],
          [
            387789.29,
            5829178.389
          ],
          [
            387791.238,
            5829179.41
          ],
          [
            387816.117,
            5829192.436
          ],
          [
            387824.193,
            5829196.664
          ],
          [
            387831.599,
            5829200.542
          ],
          [
            387839.528,
            5829205.027
          ],
          [
            387853.542,
            5829212.954
          ],
          [
            387867.341,
            5829220.759
          ],
          [
            387880.957,
            5829228.712
          ],
          [
            387894.848,
            5829236.824
          ],
          [
            387908.907,
            5829245.035
          ],
          [
            387922.577,
            5829253.018
          ],
          [
            387924.362,
            5829254.061
          ],
          [
            387936.826,
            5829260.511
          ],
          [
            387947.73,
            5829266.155
          ],
          [
            387949.648,
            5829267.108
          ],
          [
            387950.886,
            5829267.795
          ],
          [
            387964.966,
            5829275.596
          ],
          [
            387979.125,
            5829283.443
          ],
          [
            387980.731,
            5829284.332
          ],
          [
            387996.597,
            5829291.892
          ],
          [
            388004.68,
            5829295.758
          ],
          [
            388026.567,
            5829306.013
          ],
          [
            388040.692,
            5829313.958
          ],
          [
            388040.429,
            5829314.563
          ],
          [
            388039.094,
            5829317.624
          ],
          [
            388037.098,
            5829322.206
          ],
          [
            388033.822,
            5829329.721
          ],
          [
            388028.387,
            5829342.02
          ],
          [
            388026.75,
            5829345.723
          ],
          [
            388025.395,
            5829348.427
          ],
          [
            388018.234,
            5829363.668
          ],
          [
            388011.014,
            5829378.629
          ],
          [
            388002.947,
            5829393.18
          ],
          [
            387994.91,
            5829407.984
          ],
          [
            387986.559,
            5829422.363
          ],
          [
            387978.005,
            5829436.797
          ],
          [
            387968.862,
            5829451.044
          ],
          [
            387965.106,
            5829456.82
          ],
          [
            387959.814,
            5829464.957
          ],
          [
            387945.388,
            5829486.543
          ],
          [
            387943.909,
            5829488.701
          ],
          [
            387966.688,
            5829503.318
          ],
          [
            387987.215,
            5829516.491
          ],
          [
            388013.596,
            5829533.42
          ],
          [
            388011.09,
            5829536.238
          ],
          [
            387987.945,
            5829562.299
          ],
          [
            387980.947,
            5829570.179
          ],
          [
            387891.092,
            5829671.353
          ],
          [
            387882.801,
            5829680.691
          ],
          [
            387867.617,
            5829697.789
          ],
          [
            387870.253,
            5829698.628
          ],
          [
            387871.26,
            5829699.519
          ],
          [
            387853.43,
            5829719.767
          ],
          [
            387853.143,
            5829720.093
          ],
          [
            387852.126,
            5829719.192
          ],
          [
            387850.791,
            5829718.768
          ],
          [
            387848.887,
            5829718.164
          ],
          [
            387837.696,
            5829727.526
          ]
        ]
      ]
    ]
  }
}