{
    "title": "Unfälle im Straßenverkehr 1951 - Beteiligte",
    "description": "Traffic accidents in 1951 - Participants. Footnotes: ¹) Without motorcycles. ²) Carriages, etc.",
    "data": [
        {
            "Monat": "Januar",
            "Unfälle_insgesamt": 993,
            "Unfälle_durch_Zusammenstoß": 612,
            "Fußgänger": 141,
            "Fahrzeuge_insgesamt": 1733,
            "Kraftfahrzeuge_aller_Art": 1342,
            "Straßenbahnen": 64,
            "Krafträder": 75,
            "Fahrräder": 223,
            "Sonstige": 29
        },
        {
            "Monat": "Februar",
            "Unfälle_insgesamt": 984,
            "Unfälle_durch_Zusammenstoß": 559,
            "Fußgänger": 190,
            "Fahrzeuge_insgesamt": 1572,
            "Kraftfahrzeuge_aller_Art": 1140,
            "Straßenbahnen": 84,
            "Krafträder": 51,
            "Fahrräder": 267,
            "Sonstige": 30
        },
        {
            "Monat": "März",
            "Unfälle_insgesamt": 1167,
            "Unfälle_durch_Zusammenstoß": 700,
            "Fußgänger": 246,
            "Fahrzeuge_insgesamt": 1963,
            "Kraftfahrzeuge_aller_Art": 1388,
            "Straßenbahnen": 125,
            "Krafträder": 74,
            "Fahrräder": 333,
            "Sonstige": 43
        },
        {
            "Monat": "April",
            "Unfälle_insgesamt": 1285,
            "Unfälle_durch_Zusammenstoß": 767,
            "Fußgänger": 274,
            "Fahrzeuge_insgesamt": 2299,
            "Kraftfahrzeuge_aller_Art": 1509,
            "Straßenbahnen": 187,
            "Krafträder": 44,
            "Fahrräder": 534,
            "Sonstige": 25
        },
        {
            "Monat": "Mai",
            "Unfälle_insgesamt": 1521,
            "Unfälle_durch_Zusammenstoß": 901,
            "Fußgänger": 343,
            "Fahrzeuge_insgesamt": 2642,
            "Kraftfahrzeuge_aller_Art": 1557,
            "Straßenbahnen": 225,
            "Krafträder": 55,
            "Fahrräder": 765,
            "Sonstige": 40
        },
        {
            "Monat": "Juni",
            "Unfälle_insgesamt": 1750,
            "Unfälle_durch_Zusammenstoß": 1044,
            "Fußgänger": 353,
            "Fahrzeuge_insgesamt": 3060,
            "Kraftfahrzeuge_aller_Art": 1658,
            "Straßenbahnen": 304,
            "Krafträder": 63,
            "Fahrräder": 989,
            "Sonstige": 46
        },
        {
            "Monat": "Juli",
            "Unfälle_insgesamt": 1728,
            "Unfälle_durch_Zusammenstoß": 1066,
            "Fußgänger": 351,
            "Fahrzeuge_insgesamt": 3046,
            "Kraftfahrzeuge_aller_Art": 1644,
            "Straßenbahnen": 317,
            "Krafträder": 63,
            "Fahrräder": 959,
            "Sonstige": 63
        },
        {
            "Monat": "August",
            "Unfälle_insgesamt": 1651,
            "Unfälle_durch_Zusammenstoß": 964,
            "Fußgänger": 332,
            "Fahrzeuge_insgesamt": 2851,
            "Kraftfahrzeuge_aller_Art": 1474,
            "Straßenbahnen": 310,
            "Krafträder": 50,
            "Fahrräder": 985,
            "Sonstige": 32
        },
        {
            "Monat": "September",
            "Unfälle_insgesamt": 1648,
            "Unfälle_durch_Zusammenstoß": 1026,
            "Fußgänger": 314,
            "Fahrzeuge_insgesamt": 2932,
            "Kraftfahrzeuge_aller_Art": 1594,
            "Straßenbahnen": 292,
            "Krafträder": 84,
            "Fahrräder": 919,
            "Sonstige": 43
        },
        {
            "Monat": "Oktober",
            "Unfälle_insgesamt": 1746,
            "Unfälle_durch_Zusammenstoß": 1042,
            "Fußgänger": 308,
            "Fahrzeuge_insgesamt": 3043,
            "Kraftfahrzeuge_aller_Art": 1729,
            "Straßenbahnen": 306,
            "Krafträder": 108,
            "Fahrräder": 842,
            "Sonstige": 58
        },
        {
            "Monat": "November",
            "Unfälle_insgesamt": 1698,
            "Unfälle_durch_Zusammenstoß": 977,
            "Fußgänger": 308,
            "Fahrzeuge_insgesamt": 2941,
            "Kraftfahrzeuge_aller_Art": 1989,
            "Straßenbahnen": 198,
            "Krafträder": 80,
            "Fahrräder": 603,
            "Sonstige": 71
        },
        {
            "Monat": "Dezember",
            "Unfälle_insgesamt": 1476,
            "Unfälle_durch_Zusammenstoß": 802,
            "Fußgänger": 256,
            "Fahrzeuge_insgesamt": 2530,
            "Kraftfahrzeuge_aller_Art": 1841,
            "Straßenbahnen": 151,
            "Krafträder": 63,
            "Fahrräder": 421,
            "Sonstige": 54
        },
        {
            "Monat": "Zusammen 1951",
            "Unfälle_insgesamt": 17647,
            "Unfälle_durch_Zusammenstoß": 10460,
            "Fußgänger": 3416,
            "Fahrzeuge_insgesamt": 30612,
            "Kraftfahrzeuge_aller_Art": 18865,
            "Straßenbahnen": 2574,
            "Krafträder": 799,
            "Fahrräder": 7840,
            "Sonstige": 534
        },
        {
            "Monat": "Zusammen 1950",
            "Unfälle_insgesamt": 12767,
            "Unfälle_durch_Zusammenstoß": 7391,
            "Fußgänger": 2621,
            "Fahrzeuge_insgesamt": 22103,
            "Kraftfahrzeuge_aller_Art": 14537,
            "Straßenbahnen": 1456,
            "Krafträder": 666,
            "Fahrräder": 4898,
            "Sonstige": 546
        }
    ]
}